markdowncleaner/__init__.py
markdowncleaner/cli.py
markdowncleaner/markdowncleaner.py
markdowncleaner/config/__init__.py
markdowncleaner/config/default_cleaning_patterns.yaml
markdowncleaner/config/loader.py
markdowncleaner-0.3.1.dist-info/licenses/LICENSE
markdowncleaner-0.3.1.dist-info/METADATA
markdowncleaner-0.3.1.dist-info/WHEEL
markdowncleaner-0.3.1.dist-info/entry_points.txt
markdowncleaner-0.3.1.dist-info/top_level.txt
markdowncleaner-0.3.1.dist-info/RECORD
