Metadata-Version: 2.4
Name: markdowncleaner
Version: 0.3.1
Summary: A tool for cleaning and formatting markdown documents
Author-email: Johannes Himmelreich <jrhimmel@syr.edu>
License: MIT
Project-URL: Repository, https://github.com/josk0/markdowncleaner
Project-URL: Issues, https://github.com/josk0/markdowncleaner/issues
Keywords: markdown,cleaning,formatting,text processing
Classifier: Programming Language :: Python :: 3
Classifier: Programming Language :: Python :: 3.10
Classifier: Programming Language :: Python :: 3.11
Classifier: Programming Language :: Python :: 3.12
Classifier: Programming Language :: Python :: 3.13
Classifier: License :: OSI Approved :: MIT License
Classifier: Operating System :: OS Independent
Classifier: Topic :: Text Processing :: Markup :: Markdown
Classifier: Topic :: Utilities
Classifier: Development Status :: 4 - Beta
Classifier: Intended Audience :: Science/Research
Requires-Python: >=3.10
License-File: LICENSE
Requires-Dist: pyyaml>=6.0
Requires-Dist: ftfy>=6.0.3
Dynamic: license-file
